ansys/fluent/parametric/__init__.py
ansys/fluent/parametric/local/__init__.py
ansys/fluent/parametric/parameters.py
ansys_fluent_parametric-0.10.0.dist-info/LICENSE
ansys_fluent_parametric-0.10.0.dist-info/METADATA
ansys_fluent_parametric-0.10.0.dist-info/WHEEL
ansys_fluent_parametric-0.10.0.dist-info/RECORD
