Metadata-Version: 2.1
Name: ansys-fluent-parametric
Version: 0.10.0
Summary: A python wrapper for Ansys Fluent parametric workflows
Home-page: https://github.com/ansys/pyfluent-parametric
License: MIT
Author: ANSYS, Inc.
Author-email: ansys.support@ansys.com
Maintainer: PyAnsys developers
Maintainer-email: pyansys.maintainers@ansys.com
Requires-Python: >=3.9,<4.0
Classifier: Development Status :: 4 - Beta
Classifier: License :: OSI Approved :: MIT License
Classifier: Operating System :: OS Independent
Classifier: Programming Language :: Python :: 3
Classifier: Programming Language :: Python :: 3.9
Classifier: Programming Language :: Python :: 3.10
Classifier: Programming Language :: Python :: 3.11
Classifier: Programming Language :: Python :: 3.12
Requires-Dist: ansys-fluent-core (>=0.20.0,<0.21.0)
Requires-Dist: h5py (>=3.7.0)
Requires-Dist: importlib-metadata (>=4.0,<5.0) ; python_version < "3.9"
Project-URL: Documentation, https://parametric.fluent.docs.pyansys.com/
Project-URL: Repository, https://github.com/ansys/pyfluent-parametric
Project-URL: Source, https://github.com/ansys/pyfluent-parametric
Project-URL: Tracker, https://github.com/ansys/pyfluent-parametric/issues
